nadir/NAG.py
nadir/__init__.py
nadir/adabelief.py
nadir/adadelta.py
nadir/adagrad.py
nadir/adam.py
nadir/adamax.py
nadir/adamw.py
nadir/amsgrad.py
nadir/base.py
nadir/lion.py
nadir/momentum.py
nadir/nadam.py
nadir/radam.py
nadir/rmsprop.py
nadir/sgd.py
nadir-0.1.1.dist-info/LICENCE
nadir-0.1.1.dist-info/METADATA
nadir-0.1.1.dist-info/WHEEL
nadir-0.1.1.dist-info/top_level.txt
nadir-0.1.1.dist-info/RECORD
