Metadata-Version: 2.1
Name: nadir
Version: 0.1.1
Summary: Nadir: Cutting-edge PyTorch optimizers for simplicity & composability! 🔥🚀💻
Author-email: Bhavnick Minhas <bhavnicksm@gmail.com>
Maintainer-email: Bhavnick Minhas <bhavnicksm@gmail.com>
License: Apache 2.0
Project-URL: Homepage, https://github.com/OptimalFoundation/nadir
Project-URL: Bug Tracker, https://github.com/OptimalFoundation/nadir/issues
Classifier: Programming Language :: Python :: 3
Classifier: License :: OSI Approved :: Apache Software License
Classifier: Operating System :: OS Independent
Classifier: Topic :: Scientific/Engineering :: Artificial Intelligence
Requires-Python: >=3.7
License-File: LICENCE
Requires-Dist: torch >=1.13.1
Provides-Extra: test
Requires-Dist: torchvision >=0.14.1 ; extra == 'test'
Requires-Dist: tqdm ; extra == 'test'
Requires-Dist: wandb ; extra == 'test'
